denied/__init__.py
denied/authorizers.py
denied/decorators.py
denied/middleware.py
denied/py.typed
django_denied-1.3.dist-info/LICENSE
django_denied-1.3.dist-info/METADATA
django_denied-1.3.dist-info/WHEEL
django_denied-1.3.dist-info/top_level.txt
django_denied-1.3.dist-info/RECORD
